fails_components_jupyter_applet_view/__init__.py
fails_components_jupyter_applet_view/labextension/_version.py
fails_components_jupyter_applet_view/labextension/package.json
fails_components_jupyter_applet_view/labextension/schemas/@fails-components/jupyter-applet-view/package.json.orig
fails_components_jupyter_applet_view/labextension/schemas/@fails-components/jupyter-applet-view/plugin.json
fails_components_jupyter_applet_view/labextension/schemas/@fails-components/jupyter-applet-view/toolbar.json
fails_components_jupyter_applet_view/labextension/static/0.ef38f858156fb06b7141.js
fails_components_jupyter_applet_view/labextension/static/349.25cd175d77bc4ffdce3e.js
fails_components_jupyter_applet_view/labextension/static/476.7b7132d29495f1fb0fe0.js
fails_components_jupyter_applet_view/labextension/static/606.a9c48e4910d1ef6d74a8.js
fails_components_jupyter_applet_view/labextension/static/690.7b69a355804f5badc1e1.js
fails_components_jupyter_applet_view/labextension/static/690.7b69a355804f5badc1e1.js.LICENSE.txt
fails_components_jupyter_applet_view/labextension/static/730.25cd175d77bc4ffdce3e.js
fails_components_jupyter_applet_view/labextension/static/912.89780d0c592cd47b5611.js
fails_components_jupyter_applet_view/labextension/static/remoteEntry.d7962da630d0ad02d95d.js
fails_components_jupyter_applet_view/labextension/static/style.js
fails_components_jupyter_applet_view/labextension/static/third-party-licenses.json
fails_components_jupyter_applet_view-0.0.5.data/data/share/jupyter/labextensions/@fails-components/jupyter-applet-view/_version.py
fails_components_jupyter_applet_view-0.0.5.data/data/share/jupyter/labextensions/@fails-components/jupyter-applet-view/package.json
fails_components_jupyter_applet_view-0.0.5.data/data/share/jupyter/labextensions/@fails-components/jupyter-applet-view/schemas/@fails-components/jupyter-applet-view/package.json.orig
fails_components_jupyter_applet_view-0.0.5.dist-info/METADATA
fails_components_jupyter_applet_view-0.0.5.dist-info/WHEEL
fails_components_jupyter_applet_view-0.0.5.dist-info/licenses/LICENSE
fails_components_jupyter_applet_view-0.0.5.dist-info/RECORD
